minerl_navigate/__init__.py
minerl_navigate/minerl_navigate.py
minerl_navigate-1.1.0.dist-info/LICENSE
minerl_navigate-1.1.0.dist-info/METADATA
minerl_navigate-1.1.0.dist-info/WHEEL
minerl_navigate-1.1.0.dist-info/top_level.txt
minerl_navigate-1.1.0.dist-info/RECORD
