Metadata-Version: 2.1
Name: minerl-navigate
Version: 1.1.0
Summary: minerl-navigate - MineRL Navigate Video Dataset
Home-page: https://github.com/vaibhavsaxena11/minerl_navigate
Author: Vaibhav Saxena
Author-email: saxena.vaibhav96@gmail.com
License: Attribution-NonCommercial-ShareAlike 4.0 International
Platform: UNKNOWN
Classifier: Intended Audience :: Science/Research
Classifier: Programming Language :: Python :: 3
Classifier: Topic :: Scientific/Engineering :: Artificial Intelligence
Requires-Dist: numpy
Requires-Dist: tensorflow
Requires-Dist: tensorflow-datasets
